fast_konno_ohmachi/__init__.py
fast_konno_ohmachi/_precalculated.py
fast_konno_ohmachi/main.py
fast_konno_ohmachi-0.1.0.dist-info/LICENSE.txt
fast_konno_ohmachi-0.1.0.dist-info/METADATA
fast_konno_ohmachi-0.1.0.dist-info/WHEEL
fast_konno_ohmachi-0.1.0.dist-info/top_level.txt
fast_konno_ohmachi-0.1.0.dist-info/RECORD
