Metadata-Version: 2.1
Name: fast-konno-ohmachi
Version: 0.1.0
Summary: A Python library that performs Konno-Ohmachi spectral smoothing very fast
Home-page: https://github.com/jsh9/fast-konno-ohmachi
License: MIT
Classifier: License :: OSI Approved :: MIT License
Classifier: Programming Language :: Python :: 3
Classifier: Programming Language :: Python :: 3 :: Only
Requires-Python: >=3.7
License-File: LICENSE.txt
Requires-Dist: numpy
